yathoo/__init__.py
yathoo/yathoo.py
yathoo-0.2.0.dist-info/METADATA
yathoo-0.2.0.dist-info/WHEEL
yathoo-0.2.0.dist-info/top_level.txt
yathoo-0.2.0.dist-info/RECORD
