Metadata-Version: 2.1
Name: yathoo
Version: 0.2.0
Summary: A short description of your package
Home-page: UNKNOWN
Author: Yathartha Santosh Yadav
Author-email: yathartha.ys@gmail.com
License: UNKNOWN
Platform: UNKNOWN
Classifier: Programming Language :: Python :: 3
Classifier: License :: OSI Approved :: MIT License
Classifier: Operating System :: OS Independent
